DeviceServer/__init__.py
DeviceServer/api_client.py
DeviceServer/configuration.py
DeviceServer/exceptions.py
DeviceServer/rest.py
DeviceServer/api/__init__.py
DeviceServer/api/devices_api.py
DeviceServer/models/__init__.py
DeviceServer/models/db_button_state.py
DeviceServer/models/db_device_button.py
DeviceServer/models/db_device_led.py
DeviceServer/models/db_device_port.py
DeviceServer/models/db_device_temperature_port.py
DeviceServer/models/db_led_state.py
DeviceServer/models/db_port_state.py
DeviceServer/models/device.py
DeviceServer/models/device_button.py
DeviceServer/models/device_led.py
DeviceServer/models/device_port.py
DeviceServer/models/device_rx_buffer.py
DeviceServer/models/device_temperature_port.py
DeviceServer/models/device_tx_buffer.py
DeviceServer/models/get_attenuator_state200_response.py
DeviceServer/models/get_devices_led200_response.py
DeviceServer/models/get_firmware_version200_response.py
DeviceServer/models/host_config.py
DeviceServer/models/port_state.py
DeviceServer/models/temp_range.py
DeviceServer/models/temperature.py
DeviceServer-1.1.2.dist-info/METADATA
DeviceServer-1.1.2.dist-info/WHEEL
DeviceServer-1.1.2.dist-info/top_level.txt
DeviceServer-1.1.2.dist-info/RECORD
